{
   "entries":[
      {
         ".tag":"folder",
         "name":"Photos",
         "path_lower":"/photos",
         "id":"id:5A7qW6X3GsMAAAAAAAACAg"
      },
      {
         ".tag":"folder",
         "name":"Public",
         "path_lower":"/public",
         "id":"id:5A7qW6X3GsMAAAAAAAACAQ"
      },
      {
         ".tag":"file",
         "name":"Getting Started.pdf",
         "path_lower":"/getting started.pdf",
         "id":"id:5A7qW6X3GsMAAAAAAAAB_w",
         "client_modified":"2012-03-21T12:26:21Z",
         "server_modified":"2012-03-21T12:26:21Z",
         "rev":"706a51654",
         "size":246000
      },
      {
         ".tag":"folder",
         "name":"COMP325 Share",
         "path_lower":"/comp325 share",
         "id":"id:5A7qW6X3GsMAAAAAAAAB_A",
         "shared_folder_id":"111170897",
         "sharing_info":{
            "read_only":false,
            "shared_folder_id":"111170897"
         }
      },
      {
         ".tag":"folder",
         "name":"DBScale",
         "path_lower":"/dbscale",
         "id":"id:5A7qW6X3GsMAAAAAAAAB-A"
      },
      {
         ".tag":"file",
         "name":"tpcc.tar",
         "path_lower":"/tpcc.tar",
         "id":"id:5A7qW6X3GsMAAAAAAAABdA",
         "client_modified":"2013-11-19T07:35:48Z",
         "server_modified":"2013-11-19T07:35:48Z",
         "rev":"51b06a51654",
         "size":78868480
      },
      {
         ".tag":"file",
         "name":"tpcc.sql",
         "path_lower":"/tpcc.sql",
         "id":"id:5A7qW6X3GsMAAAAAAAABcw",
         "client_modified":"2013-11-19T07:35:50Z",
         "server_modified":"2013-11-19T07:35:49Z",
         "rev":"51c06a51654",
         "size":7532
      },
      {
         ".tag":"file",
         "name":"ZtarCraftPlus.zip",
         "path_lower":"/ztarcraftplus.zip",
         "id":"id:5A7qW6X3GsMAAAAAAAABcg",
         "client_modified":"2013-12-12T08:10:29Z",
         "server_modified":"2013-12-12T08:10:29Z",
         "rev":"51d06a51654",
         "size":104311916
      },
      {
         ".tag":"folder",
         "name":"WOW",
         "path_lower":"/wow",
         "id":"id:5A7qW6X3GsMAAAAAAAABcQ"
      },
      {
         ".tag":"file",
         "name":"Audio 4_bip.wav",
         "path_lower":"/audio 4_bip.wav",
         "id":"id:5A7qW6X3GsMAAAAAAAABWg",
         "client_modified":"2014-09-01T00:58:30Z",
         "server_modified":"2014-09-01T00:58:30Z",
         "rev":"53706a51654",
         "size":8378344
      },
      {
         ".tag":"file",
         "name":"round1.mp3",
         "path_lower":"/round1.mp3",
         "id":"id:5A7qW6X3GsMAAAAAAAABWQ",
         "client_modified":"2014-09-08T02:28:03Z",
         "server_modified":"2014-09-08T02:28:02Z",
         "rev":"53806a51654",
         "size":1436651
      },
      {
         ".tag":"file",
         "name":"t3r1.wav",
         "path_lower":"/t3r1.wav",
         "id":"id:5A7qW6X3GsMAAAAAAAABWA",
         "client_modified":"2014-09-16T00:09:59Z",
         "server_modified":"2014-09-16T00:10:25Z",
         "rev":"53b06a51654",
         "size":26020586
      },
      {
         ".tag":"file",
         "name":"chris brainstorm.mp3",
         "path_lower":"/chris brainstorm.mp3",
         "id":"id:5A7qW6X3GsMAAAAAAAABVw",
         "client_modified":"2014-09-20T00:31:10Z",
         "server_modified":"2014-09-20T00:31:10Z",
         "rev":"53c06a51654",
         "size":10685565
      },
      {
         ".tag":"file",
         "name":"round 2 test.wav",
         "path_lower":"/round 2 test.wav",
         "id":"id:5A7qW6X3GsMAAAAAAAABVg",
         "client_modified":"2014-09-20T22:18:09Z",
         "server_modified":"2014-09-20T22:18:18Z",
         "rev":"53f06a51654",
         "size":4343018
      },
      {
         ".tag":"file",
         "name":"demo.mp4",
         "path_lower":"/demo.mp4",
         "id":"id:5A7qW6X3GsMAAAAAAAABVQ",
         "client_modified":"2014-09-23T20:23:12Z",
         "server_modified":"2014-09-23T20:23:12Z",
         "rev":"54006a51654",
         "size":234961400
      },
      {
         ".tag":"file",
         "name":"Audio 5_bip.aif",
         "path_lower":"/audio 5_bip.aif",
         "id":"id:5A7qW6X3GsMAAAAAAAABVA",
         "client_modified":"2014-09-23T21:17:39Z",
         "server_modified":"2014-09-23T21:17:39Z",
         "rev":"54106a51654",
         "size":6209866
      },
      {
         ".tag":"file",
         "name":"Audio 6_bip.aif",
         "path_lower":"/audio 6_bip.aif",
         "id":"id:5A7qW6X3GsMAAAAAAAABUw",
         "client_modified":"2014-09-23T21:17:41Z",
         "server_modified":"2014-09-23T21:17:41Z",
         "rev":"54206a51654",
         "size":3351626
      },
      {
         ".tag":"file",
         "name":"keep_bip.aif",
         "path_lower":"/keep_bip.aif",
         "id":"id:5A7qW6X3GsMAAAAAAAABUg",
         "client_modified":"2014-09-23T21:17:46Z",
         "server_modified":"2014-09-23T21:17:46Z",
         "rev":"54306a51654",
         "size":11039306
      },
      {
         ".tag":"file",
         "name":"Audio 1_bip.wav",
         "path_lower":"/audio 1_bip.wav",
         "id":"id:5A7qW6X3GsMAAAAAAAAADg",
         "client_modified":"2014-09-29T21:33:10Z",
         "server_modified":"2014-09-29T21:33:10Z",
         "rev":"54406a51654",
         "size":18727146
      },
      {
         ".tag":"folder",
         "name":"BVW_round3",
         "path_lower":"/bvw_round3",
         "id":"id:5A7qW6X3GsMAAAAAAAAADw",
         "shared_folder_id":"723128703",
         "sharing_info":{
            "read_only":false,
            "shared_folder_id":"723128703"
         }
      },
      {
         ".tag":"file",
         "name":"jerry_voice.wav",
         "path_lower":"/jerry_voice.wav",
         "id":"id:5A7qW6X3GsMAAAAAAAAAEA",
         "client_modified":"2014-10-06T20:37:16Z",
         "server_modified":"2014-10-06T20:37:16Z",
         "rev":"54606a51654",
         "size":19417066
      },
      {
         ".tag":"folder",
         "name":"Scrolling",
         "path_lower":"/scrolling",
         "id":"id:5A7qW6X3GsMAAAAAAAACBA",
         "shared_folder_id":"784794952",
         "sharing_info":{
            "read_only":false,
            "shared_folder_id":"784794952"
         }
      }
   ],
   "cursor":"AAEB3lMfkU7qTi82p0_1k8TDeatJN2KmpOLULi_vc-N4LE_1MzEMwk2Zzx_F0Nqdsfp9ArI966sb10za3iLdlcTdeHINzyNTpn1cgB-K2djEJIadIbgLjbqTAE0dZw4RF2mdbKda4s37xbAq85a9mFPL",
   "has_more":false
}